cone.tokens-0.5-py3.9-nspkg.pth
cone/tokens/__init__.py
cone/tokens/api.py
cone/tokens/exceptions.py
cone/tokens/model.py
cone/tokens/settings.py
cone/tokens/browser/__init__.py
cone/tokens/browser/api.py
cone/tokens/browser/settings.py
cone/tokens/browser/token.py
cone/tokens/browser/tokens.py
cone/tokens/browser/static/cone.tokens.css
cone/tokens/browser/static/cone.tokens.js
cone/tokens/browser/static/cone.tokens.min.css
cone/tokens/browser/static/cone.tokens.min.js
cone/tokens/browser/templates/token.pt
cone/tokens/browser/templates/tokens.pt
cone/tokens/browser/templates/tokens_overview.pt
cone/tokens/locale/cone.tokens.pot
cone/tokens/locale/de/LC_MESSAGES/cone.tokens.mo
cone/tokens/locale/de/LC_MESSAGES/cone.tokens.po
cone/tokens/locale/en/LC_MESSAGES/cone.tokens.mo
cone/tokens/locale/en/LC_MESSAGES/cone.tokens.po
cone/tokens/tests/__init__.py
cone/tokens/tests/test_api.py
cone/tokens/tests/test_json_api.py
cone/tokens/tests/test_model.py
cone/tokens/tests/test_settings.py
cone/tokens/tests/test_token.py
cone.tokens-0.5.dist-info/LICENSE.rst
cone.tokens-0.5.dist-info/METADATA
cone.tokens-0.5.dist-info/WHEEL
cone.tokens-0.5.dist-info/namespace_packages.txt
cone.tokens-0.5.dist-info/top_level.txt
cone.tokens-0.5.dist-info/RECORD
