Metadata-Version: 2.1
Name: cone.tokens
Version: 0.5
Summary: cone token api
Home-page: http://github.com/conestack/cone.tokens
Author: Cone Contributors
Author-email: dev@conestack.org
License: MIT
Keywords: node pyramid cone web
Classifier: Environment :: Web Environment
Classifier: Programming Language :: Python
Classifier: Topic :: Internet :: WWW/HTTP :: Dynamic Content
License-File: LICENSE.rst
Requires-Dist: setuptools
Requires-Dist: cone.sql
Requires-Dist: python-dateutil
Requires-Dist: qrcode[pil]
Provides-Extra: test
Requires-Dist: zope.testrunner ; extra == 'test'
